KEYPAD(100pt)/design.sv
`timescale 1ns / 1ps
//////////////////////////////////////////////////////////////////////////////////
// Company: 
// Engineer: 
// 
// Create Date:    16:10:14 01/06/2021 
// Design Name: 
// Module Name:    phone 
// Project Name: 
// Target Devices: 
// Tool versions: 
// Description: 
//
// Dependencies: 
//
// Revision: 
// Revision 0.01 - File Created
// Additional Comments: 
//
//////////////////////////////////////////////////////////////////////////////////
module phone (input clk,
 input rst,
 input Keypressed,
 input [7:0] button,
 output reg [63:0] statusMsg
 );
/////////////////////////////////////////////////////////////////////////
parameter [2:0]idle 	  = 3'b000; 
parameter [2:0]ringing 	  = 3'b001;
parameter [2:0]cost 	  = 3'b010;

/////////////////////////////////////////////////////////////////////////
reg [31:0] counter;
reg [3:0] valid;
reg [7:0] currentstate;
reg [7:0] next_state;
reg[3:0]key;
/////////////////////////////////////////////////////////////////////////
always@(posedge clk or posedge rst)
begin:phone
if(rst)begin
statusMsg[63:0]<="        ";
currentstate<= idle;
counter<=0;

end
//////////////////////////////////////////////////////////////////////////////////////////
case(currentstate)
//////////////////////////////////////////////////////////////////////////////////////////
idle:begin
  key[0]<=1;
  key[1]<=2;
  key[2]<=3;
  key[3]<=4;
if(Keypressed)begin currentstate<=ringing;
end
end
//////////////////////////////////////////////////////////////////////////////////////////
ringing:begin
  if(Keypressed==0)begin
      if(counter==0)
        begin
          valid[0]<=button;
		  counter<=counter+1;
		  currentstate<=idle;
        end	
	if(counter==1)
        begin
          valid[1]<=button;
		  counter<=counter+1;
		  currentstate<=idle;
        end	
	if(counter==2)
        begin
          valid[2]<=button;
		  counter<=counter+1;
		  currentstate<=idle;
        end		
	if(counter==3)begin 
      valid[3]<=button;
	currentstate<=cost;end
    end
end


cost:begin
if(valid==key)begin
statusMsg<="VALID   ";
  currentstate<=idle;end
else
  begin
statusMsg<="INVALID ";
currentstate<=idle;
end
end
default: currentstate<=idle;
endcase

end
endmodule

KEYPAD(100pt)/testbench.sv
`timescale 1ns / 1ps

////////////////////////////////////////////////////////////////////////////////
// Company: 
// Engineer:
//
// Create Date:   16:10:43 01/06/2021
// Design Name:   phone
// Module Name:   C:/Users/orkun/projects/OrkunErdemTermProject20701/test.v
// Project Name:  OrkunErdemTermProject20701
// Target Device:  
// Tool versions:  
// Description: 
//
// Verilog Test Fixture created by ISE for module: phone
//
// Dependencies:
// 
// Revision:
// Revision 0.01 - File Created
// Additional Comments:
// 
////////////////////////////////////////////////////////////////////////////////

module test;

	// Inputs
	reg clk;
	reg rst;
	reg Keypressed;
  reg [7:0] button;

	// Outputs
	wire [63:0] statusMsg;

	// Instantiate the Unit Under Test (UUT)
	phone uut (
		.clk(clk), 
		.rst(rst), 
		.Keypressed(Keypressed), 
      .button(button), 
		.statusMsg(statusMsg)
	);

	always #5 clk = ~clk; 

initial begin
	// initialize every input to 0
	clk = 0;
	rst = 0;
	Keypressed = 0;
	button = 0;
	 
	
	// reset your circuit
	rst=1; #20; rst=0; #20; rst=0;              // reset
  
  Keypressed=1;#10;Keypressed=0;button=1;#10;
  Keypressed=1;#10;Keypressed=0;button=2;#10;
  Keypressed=1;#10;Keypressed=0;button=3;#10;
  Keypressed=1;#10;Keypressed=0;button=4;#10;
	#50;
  	rst=1; #20; rst=0; #20;
	Keypressed=1;#10;Keypressed=0;button=3;#10;
	Keypressed=1;#10;Keypressed=0;button=4;#10;
	Keypressed=1;#10;Keypressed=0;button=2;#10;
	Keypressed=1;#10;Keypressed=0;button=1;#10;


	

	
end

always #5 clk = ~clk;
  initial #400 $finish;
   initial
     begin
	$dumpfile("dump.vcd");
	$dumpvars;
     end

endmodule

KEYPAD(100pt)/dump.vcd
$date
	Thu May 27 20:16:31 2021
$end
$version
	Icarus Verilog
$end
$timescale
	1ps
$end
$scope module test $end
$var wire 64 ! statusMsg [63:0] $end
$var reg 1 " Keypressed $end
$var reg 8 # button [7:0] $end
$var reg 1 $ clk $end
$var reg 1 % rst $end
$scope module uut $end
$var wire 1 & Keypressed $end
$var wire 8 ' button [7:0] $end
$var wire 1 ( clk $end
$var wire 1 ) rst $end
$var reg 32 * counter [31:0] $end
$var reg 8 + currentstate [7:0] $end
$var reg 4 , key [3:0] $end
$var reg 64 - statusMsg [63:0] $end
$var reg 4 . valid [3:0] $end
$scope begin phone $end
$upscope $end
$upscope $end
$upscope $end
$enddefinitions $end
#0
$dumpvars
bx .
b10000000100000001000000010000000100000001000000010000000100000 -
bx ,
b0 +
b0 *
1)
0(
b0 '
0&
1%
0$
b0 #
0"
b10000000100000001000000010000000100000001000000010000000100000 !
$end
#5000
b101 ,
0$
0(
#10000
b101 ,
0$
0(
#15000
b101 ,
0$
0(
#20000
b101 ,
0$
0(
0%
0)
#25000
b101 ,
0$
0(
#30000
b101 ,
0$
0(
#35000
b101 ,
0$
0(
#40000
b1 +
b101 ,
0$
0(
1"
1&
#45000
0$
0(
#50000
b0 +
b1 *
bx1 .
0$
0(
b1 #
b1 '
0"
0&
#55000
b101 ,
0$
0(
#60000
b1 +
b101 ,
0$
0(
1"
1&
#65000
0$
0(
#70000
b0 +
b10 *
bx01 .
0$
0(
b10 #
b10 '
0"
0&
#75000
b101 ,
0$
0(
#80000
b1 +
b101 ,
0$
0(
1"
1&
#85000
0$
0(
#90000
b0 +
b11 *
bx101 .
0$
0(
b11 #
b11 '
0"
0&
#95000
b101 ,
0$
0(
#100000
b1 +
b101 ,
0$
0(
1"
1&
#105000
0$
0(
#110000
b10 +
b101 .
0$
0(
b100 #
b100 '
0"
0&
#115000
b0 +
b101011001000001010011000100100101000100001000000010000000100000 -
b101011001000001010011000100100101000100001000000010000000100000 !
0$
0(
#120000
b101 ,
0$
0(
#125000
b101 ,
0$
0(
#130000
b101 ,
0$
0(
#135000
b101 ,
0$
0(
#140000
b101 ,
0$
0(
#145000
b101 ,
0$
0(
#150000
b101 ,
0$
0(
#155000
b101 ,
0$
0(
#160000
b101 ,
0$
0(
#165000
b101 ,
0$
0(
#170000
b101 ,
b0 *
b10000000100000001000000010000000100000001000000010000000100000 -
b10000000100000001000000010000000100000001000000010000000100000 !
0$
0(
1%
1)
#175000
b101 ,
0$
0(
#180000
b101 ,
0$
0(
#185000
b101 ,
0$
0(
#190000
b101 ,
0$
0(
0%
0)
#195000
b101 ,
0$
0(
#200000
b101 ,
0$
0(
#205000
b101 ,
0$
0(
#210000
b1 +
b101 ,
0$
0(
1"
1&
#215000
0$
0(
#220000
b0 +
b1 *
b101 .
0$
0(
b11 #
b11 '
0"
0&
#225000
b101 ,
0$
0(
#230000
b1 +
b101 ,
0$
0(
1"
1&
#235000
0$
0(
#240000
b0 +
b10 *
b101 .
0$
0(
b100 #
b100 '
0"
0&
#245000
b101 ,
0$
0(
#250000
b1 +
b101 ,
0$
0(
1"
1&
#255000
0$
0(
#260000
b0 +
b11 *
b1 .
0$
0(
b10 #
b10 '
0"
0&
#265000
b101 ,
0$
0(
#270000
b1 +
b101 ,
0$
0(
1"
1&
#275000
0$
0(
#280000
b10 +
b1001 .
0$
0(
b1 #
b1 '
0"
0&
#285000
b0 +
b100100101001110010101100100000101001100010010010100010000100000 -
b100100101001110010101100100000101001100010010010100010000100000 !
0$
0(
#290000
b101 ,
0$
0(
#295000
b101 ,
0$
0(
#300000
b101 ,
0$
0(
#305000
b101 ,
0$
0(
#310000
b101 ,
0$
0(
#315000
b101 ,
0$
0(
#320000
b101 ,
0$
0(
#325000
b101 ,
0$
0(
#330000
b101 ,
0$
0(
#335000
b101 ,
0$
0(
#340000
b101 ,
0$
0(
#345000
b101 ,
0$
0(
#350000
b101 ,
0$
0(
#355000
b101 ,
0$
0(
#360000
b101 ,
0$
0(
#365000
b101 ,
0$
0(
#370000
b101 ,
0$
0(
#375000
b101 ,
0$
0(
#380000
b101 ,
0$
0(
#385000
b101 ,
0$
0(
#390000
b101 ,
0$
0(
#395000
b101 ,
0$
0(
#400000
b101 ,
0$
0(
